autotest/__init__.py
autotest/conftest.py
autotest/test_benchmark.py
autotest/test_mup3d.py
autotest/test_notebooks.py
autotest/test_utils.py
mf6rtm/__init__.py
mf6rtm/__main__.py
mf6rtm/py.typed
mf6rtm/assets/__init__.py
mf6rtm/config/__init__.py
mf6rtm/config/config.py
mf6rtm/config/yaml_reader.py
mf6rtm/io/__init__.py
mf6rtm/io/externalio.py
mf6rtm/mup3d/__init__.py
mf6rtm/mup3d/base.py
mf6rtm/simulation/__init__.py
mf6rtm/simulation/discretization.py
mf6rtm/simulation/mf6api.py
mf6rtm/simulation/phreeqcbmi.py
mf6rtm/simulation/solver.py
mf6rtm/utils/__init__.py
mf6rtm/utils/utils.py
mf6rtm-0.3.0.dist-info/licenses/LICENSE
mf6rtm-0.3.0.dist-info/METADATA
mf6rtm-0.3.0.dist-info/WHEEL
mf6rtm-0.3.0.dist-info/entry_points.txt
mf6rtm-0.3.0.dist-info/top_level.txt
mf6rtm-0.3.0.dist-info/RECORD
