Metadata-Version: 2.4
Name: mf6rtm
Version: 0.3.0
Summary: Reactive transport model through MODFLOW 6 and PHREEQCRM
Author: Pablo Ortega
Author-email: portega@intera.com
License: BSD 3-Clause
Keywords: MODFLOW,PHREEQCRM,reactive transport,groundwater,hydrology
Platform: unix
Platform: linux
Platform: osx
Platform: cygwin
Platform: win32
Classifier: Development Status :: 3 - Alpha
Classifier: Programming Language :: Python :: 3
Classifier: Programming Language :: Python :: 3 :: Only
Classifier: Programming Language :: Python :: 3.10
Classifier: Programming Language :: Python :: 3.11
Classifier: Programming Language :: Python :: 3.12
Classifier: Programming Language :: Python :: 3.13
Classifier: License :: OSI Approved :: BSD License
Classifier: Topic :: Scientific/Engineering :: Hydrology
Requires-Python: >=3.10
License-File: LICENSE
Requires-Dist: phreeqcrm
Requires-Dist: modflowapi
Requires-Dist: flopy
Requires-Dist: toml
Provides-Extra: testing
Requires-Dist: pytest>=7.0; extra == "testing"
Requires-Dist: pytest-cov>=2.0; extra == "testing"
Requires-Dist: mypy>=1.10; extra == "testing"
Requires-Dist: flake8>=3.9; extra == "testing"
Requires-Dist: tox>=3.24; extra == "testing"
Requires-Dist: flaky>=3.8; extra == "testing"
Requires-Dist: jupytext>=1.16.0; extra == "testing"
Requires-Dist: nbconvert>=7.16; extra == "testing"
Requires-Dist: ipykernel>=6.29; extra == "testing"
Provides-Extra: docs
Requires-Dist: sphinx; extra == "docs"
Requires-Dist: sphinx_rtd_theme; extra == "docs"
Requires-Dist: myst-parser; extra == "docs"
Requires-Dist: sphinx-autodoc-typehints; extra == "docs"
Dynamic: license-file
